DESCRIPTION.rst
MANIFEST.in
README.rst
setup.cfg
setup.py
marcopolo/__init__.py
marcopolo.bindings.egg-info/PKG-INFO
marcopolo.bindings.egg-info/SOURCES.txt
marcopolo.bindings.egg-info/dependency_links.txt
marcopolo.bindings.egg-info/namespace_packages.txt
marcopolo.bindings.egg-info/requires.txt
marcopolo.bindings.egg-info/top_level.txt
marcopolo/bindings/__init__.py
marcopolo/bindings/marco.py
marcopolo/bindings/polo.py
marcopolo/bindings/types.py
marcopolo/bindings/utils.py