Metadata-Version: 1.1
Name: marcopolo.bindings
Version: 0.1.3
Summary: A python binding for MarcoPolo
Home-page: UNKNOWN
Author: Diego Martín
Author-email: martinarroyo@usal.es
License: MIT
Keywords: marcopolo discovery binding
Platform: UNKNOWN
Classifier: Development Status :: 3 - Alpha
Classifier: Intended Audience :: Developers
Classifier: Intended Audience :: System Administrators
Classifier: Topic :: Software Development :: Libraries :: Python Modules
Classifier: License :: OSI Approved :: Mozilla Public License 2.0 (MPL 2.0)
Classifier: Programming Language :: Python :: 2.7
Classifier: Programming Language :: Python :: 3.4
Classifier: Natural Language :: English
Provides: marcopolo.bindings
